{
	"invocation": "sweets timesheet",
	"intents": [
		{
			"name": "CatchAllIntent",
			"phrases": [
				"today I'm working in {anything}",
				"today I'm working on {anything}",
				"today I'm working at {anything}",
				"I'm working on {anything}",
				"I'm working in {anything}",
				"I'm working at {anything}",
				"today I worked on {anything}",
				"today I did {anything}",
				"today I {anything}",
				"I worked on {anything}",
				"I built a {anything}",
				"I built {anything}",
				"I did {anything}",
				"I {anything}",
				"{anything}"
			],
			"inputs": [
				{
					"name": "anything",
					"type": {
						"dialogflow": "@sys.any"
					}
				}
			]
		}
	],
	"inputTypes": [
		{
			"name": "yesNoInputType",
			"values": [
				{
					"value": "yes",
					"synonyms": [
						"yeah",
						"yessir",
						"absolutely",
						"please",
						"that sounds right",
						"correct",
						"yes please",
						"yea",
						"yup",
						"affirmative",
						"you know it",
						"affirm",
						"approve",
						"alright",
						"all right",
						"very well",
						"of course",
						"by all means",
						"sure",
						"certainly"
					]
				},
				{
					"value": "no",
					"synonyms": [
						"nope",
						"no thank you",
						"by no means",
						"not at all",
						"negative",
						"never",
						"that sourds wrong",
						"incorrect",
						"no thanks",
						"nah",
						"decline",
						"deny"
					]
				}
			]
		}
	],
	"alexa": {
		"interactionModel": {
			"languageModel": {
				"intents": [
					{
						"name": "AMAZON.CancelIntent",
						"samples": []
					},
					{
						"name": "AMAZON.HelpIntent",
						"samples": []
					},
					{
						"name": "AMAZON.StopIntent",
						"samples": []
					}
				]
			}
		}
	},
	"dialogflow": {
		"intents": [
			{
				"name": "Default Fallback Intent",
				"auto": true,
				"webhookUsed": true,
				"fallbackIntent": true
			},
			{
				"name": "Default Welcome Intent",
				"auto": true,
				"webhookUsed": true,
				"events": [
					{
						"name": "WELCOME"
					}
				]
			}
		]
	}
}